amis/README.md
amis/__init__.py
amis/components.py
amis/constants.py
amis/types.py
amis/utils.py
amis/templates/app.html
amis/templates/page.html
amis-0.1.1.dist-info/WHEEL
amis-0.1.1.dist-info/METADATA
amis-0.1.1.dist-info/RECORD
