Metadata-Version: 2.1
Name: amis
Version: 0.1.1
Summary: amis是Baidu团队开发的一个低代码前端框架，它使用JSON配置来生成页面，可以减少页面开发工作量，极大提升效率。python amis基于baidu amis,对amis数据结构通过pydantic转换为对应的python数据模型,并添加部分常用方法.
Keywords: amis,fastapi-amis-admin
Author-email: Atomi <1456417373@qq.com>
Maintainer-email: Atomi <1456417373@qq.com>
Requires-Python: >=3.6.1
Classifier: Framework :: FastAPI
Classifier: Environment :: Web Environment
Classifier: Topic :: System :: Systems Administration
Classifier: License :: OSI Approved :: Apache Software License
Classifier: Operating System :: OS Independent
Classifier: Programming Language :: Python :: 3
Classifier: Programming Language :: Python :: 3.6
Classifier: Programming Language :: Python :: 3.7
Classifier: Programming Language :: Python :: 3.8
Classifier: Programming Language :: Python :: 3.9
Classifier: Programming Language :: Python :: 3.10
Requires-Dist: ujson>=4.0.1
Requires-Dist: pydantic>=1.6.2
Requires-Dist: pytest >=6.2.4,<7.0.0 ; extra == "test"
Project-URL: Documentation, https://docs.gh.amis.work/amis/types/
Project-URL: FastAPI-Amis-Admin, https://github.com/amisadmin/fastapi_amis_admin
Project-URL: Source, https://github.com/amisadmin/fastapi_amis_admin
Provides-Extra: test
